<?xml version="1.0" encoding="UTF-8"?>
<con:soapui-project id="71536eeb-dca0-497c-bcc0-fd4558ab2369" activeEnvironment="Default" name="WIX POC" soapui-version="5.6.0" abortOnError="false" runType="SEQUENTIAL" resourceRoot="" xmlns:con="http://eviware.com/soapui/config"><con:settings/><con:interface xsi:type="con:RestService" id="89daa723-b6ec-4108-afe4-421789babebb" wadlVersion="http://wadl.dev.java.net/2009/02" name="https://splitspot.com" type="rest" xmlns:xsi="http://www.w3.org/2001/XMLSchema-instance"><con:settings/><con:definitionCache/><con:endpoints><con:endpoint>https://splitspot.com</con:endpoint></con:endpoints><con:resource name="UpdateRoom - Published" path="/_functions/updateRoom" id="15647813-aaff-4c3d-8815-f1f5b976e044"><con:settings/><con:parameters/><con:method name="UpdateRoom 1" id="bd45d9cf-de80-4d14-aa51-4489ae493653" method="POST"><con:settings/><con:parameters/><con:representation type="FAULT"><con:mediaType>application/json;charset=utf-8</con:mediaType><con:status>400 500</con:status><con:params/><con:element xmlns:upd="https://splitspot.com/_functions/updateRoom">upd:Fault</con:element></con:representation><con:representation type="REQUEST"><con:mediaType>application/json</con:mediaType><con:params/></con:representation><con:representation type="REQUEST"><con:mediaType>application/x-www-form-urlencoded</con:mediaType><con:params/></con:representation><con:representation type="FAULT"><con:mediaType>text/html;charset=utf-8</con:mediaType><con:status>500</con:status><con:params/></con:representation><con:representation type="RESPONSE"><con:mediaType>application/json;charset=utf-8</con:mediaType><con:status>200</con:status><con:params/><con:element xmlns:upd="https://splitspot.com/_functions/updateRoom">upd:Response</con:element></con:representation><con:request name="Request 1" id="0cbb1818-ecbb-4318-9f6f-e14091bc9ad9" mediaType="application/json" postQueryString="false"><con:settings><con:setting id="com.eviware.soapui.impl.wsdl.WsdlRequest@request-headers">&lt;xml-fragment/></con:setting></con:settings><con:endpoint>https://splitspot.com</con:endpoint><con:request>{
	"idRoom":"00000000-0000-0000-0000-000000000003",
	"option":"title",
	"value": "This is a new title"
}
</con:request><con:originalUri>https://splitspot.com/_functions/updateRoom</con:originalUri><con:credentials><con:authType>No Authorization</con:authType></con:credentials><con:jmsConfig JMSDeliveryMode="PERSISTENT"/><con:jmsPropertyConfig/><con:parameters/><con:parameterOrder/></con:request></con:method></con:resource><con:resource name="UpdateRoom - Dev" path="/_functions-dev/test" id="6f6bc412-a1a4-4061-9b8c-26bfd10b5053"><con:settings/><con:parameters/><con:method name="Room Update" id="43b56a28-95bb-4b39-9e6e-f77ecbc30d85" method="POST"><con:settings/><con:parameters/><con:representation type="REQUEST"><con:mediaType>application/json</con:mediaType><con:params/></con:representation><con:representation type="RESPONSE"><con:mediaType>application/json;charset=utf-8</con:mediaType><con:status>200</con:status><con:params/><con:element xmlns:upd="https://splitspot.com/_functions-dev/updateRoom">upd:Response</con:element></con:representation><con:representation type="FAULT"><con:mediaType>application/json;charset=utf-8</con:mediaType><con:status>400 404 500</con:status><con:params/><con:element xmlns:upd="https://splitspot.com/_functions-dev/updateRoom">upd:Fault</con:element></con:representation><con:representation type="FAULT"><con:mediaType>text/html;charset=utf-8</con:mediaType><con:status>404 400</con:status><con:params/></con:representation><con:request name="Request 1" id="27f313d6-de26-478c-8475-f0c965b78aa1" mediaType="application/json" postQueryString="false"><con:settings><con:setting id="com.eviware.soapui.impl.wsdl.WsdlRequest@request-headers">&lt;xml-fragment/></con:setting></con:settings><con:endpoint>https://splitspot.com</con:endpoint><con:request>{"unitId": "00000000-0000-0000-0000-000000000001", "unitPrice": 1050.0, "unitAvailability": [true, "Available Now!", "1/3 Rooms Available"], "rooms": ["A", "B", "C"], "roomsPrice": [1050.0, 1450.0, 1250.0], "roomsAvailability": ["Available Now!", "Not Available", "Not Available"]}</con:request><con:originalUri>https://splitspot.com/_functions-dev/updateRoom</con:originalUri><con:credentials><con:authType>No Authorization</con:authType></con:credentials><con:jmsConfig JMSDeliveryMode="PERSISTENT"/><con:jmsPropertyConfig/><con:parameters/><con:parameterOrder/></con:request></con:method></con:resource><con:resource name="test" path="/_functions-dev/test" id="da71a054-4f4f-441b-9a0e-7213d88b73e2"><con:settings/><con:parameters/><con:method name="Method 1" id="a6cb6b41-2366-45ad-b93d-7a9dcfb80392" method="GET"><con:settings/><con:parameters/><con:representation type="RESPONSE"><con:mediaType>application/json;charset=utf-8</con:mediaType><con:status>200</con:status><con:params/><con:element xmlns:test="https://splitspot.com/_functions-dev/test">test:Response</con:element></con:representation><con:representation type="FAULT"><con:mediaType>text/html;charset=utf-8</con:mediaType><con:status>500</con:status><con:params/></con:representation><con:request name="Request 1" id="73813ddf-4488-4954-b62c-f000ae6612bf" mediaType="application/json"><con:settings><con:setting id="com.eviware.soapui.impl.wsdl.WsdlRequest@request-headers">&lt;xml-fragment/></con:setting></con:settings><con:endpoint>https://splitspot.com</con:endpoint><con:request/><con:originalUri>https://splitspot.com/_functions-dev/test</con:originalUri><con:credentials><con:authType>No Authorization</con:authType></con:credentials><con:jmsConfig JMSDeliveryMode="PERSISTENT"/><con:jmsPropertyConfig/><con:parameters/></con:request></con:method></con:resource><con:resource name="batchUpdate" path="/_functions-dev/batchUpdate" id="73e29639-47ab-4b63-809d-470fd5b4eff4"><con:settings/><con:parameters/><con:method name="Method 1" id="da714b74-b5fa-410f-9887-2c4c11837b8a" method="POST"><con:settings/><con:parameters/><con:representation type="FAULT"><con:mediaType>text/html;charset=utf-8</con:mediaType><con:status>400 500 404</con:status><con:params/></con:representation><con:representation type="REQUEST"><con:mediaType>application/json</con:mediaType><con:params/></con:representation><con:representation type="RESPONSE"><con:mediaType>application/json;charset=utf-8</con:mediaType><con:status>200</con:status><con:params/><con:element xmlns:bat="https://splitspot.com/_functions-dev/batchUpdate">bat:Response</con:element></con:representation><con:representation type="FAULT"><con:mediaType>application/json;charset=utf-8</con:mediaType><con:status>500</con:status><con:params/><con:element xmlns:bat="https://splitspot.com/_functions-dev/batchUpdate">bat:Fault</con:element></con:representation><con:request name="Request 1" id="0f981059-83d0-43d7-aeab-a266ddfd78c5" mediaType="application/json" postQueryString="false"><con:settings><con:setting id="com.eviware.soapui.impl.wsdl.WsdlRequest@request-headers">&lt;xml-fragment/></con:setting></con:settings><con:endpoint>https://splitspot.com</con:endpoint><con:request>{
	'unitId': '7b94504c-b990-4bb6-91ad-acf557ebe8f9', 
	'unitPrice': 1313.0, 
	'unitAvailability': [true, 'Available November 1st', '6/6 Rooms Available'], 
	'rooms': ['A', 'B', 'C', 'D', 'E', 'F'], 
	'roomsPrice': [null, null, null, 1313.0, 1313.0, 1349.0], 
	'roomsAvailability': ['Available December 1st', 'Available December 1st', 'Available January 1st', 'Available November 1st', 'Available November 1st', 'Available November 1st']
}</con:request><con:originalUri>https://splitspot.com/_functions-dev/batchUpdate</con:originalUri><con:credentials><con:authType>No Authorization</con:authType></con:credentials><con:jmsConfig JMSDeliveryMode="PERSISTENT"/><con:jmsPropertyConfig/><con:parameters/></con:request><con:request name="success" id="9f4061b0-0c03-4a6c-9a33-87eeb1ea7bec" mediaType="application/json" postQueryString="false"><con:settings><con:setting id="com.eviware.soapui.impl.wsdl.WsdlRequest@request-headers">&lt;xml-fragment/></con:setting></con:settings><con:endpoint>https://splitspot.com</con:endpoint><con:request>{
	"unitId":"5d2a2e78-4d75-4803-9eba-e085ac1308a4",
	"unitPrice":null,
	"unitAvailability":[false,"Not Available","0/5 Rooms Available"],
	"rooms":["A","B","C","D","E"],
	"roomsPrice":[null,null,null,null,null],
	"roomsAvailability":["Not Available","Available Now!","Not Available","Not Available","Not Available"]
}</con:request><con:originalUri>https://splitspot.com/_functions-dev/batchUpdate</con:originalUri><con:credentials><con:authType>No Authorization</con:authType></con:credentials><con:jmsConfig JMSDeliveryMode="PERSISTENT"/><con:jmsPropertyConfig/><con:parameters/></con:request></con:method></con:resource></con:interface><con:properties/><con:wssContainer/><con:oAuth2ProfileContainer/><con:oAuth1ProfileContainer/><con:sensitiveInformation/></con:soapui-project>